tf2pb/.__data__.pys
tf2pb/__init__.py
tf2pb/convert_ckpt.py
tf2pb/convert_ckpt_dtype.py
tf2pb/convert_keras.py
tf2pb/optimization.py
tf2pb/run_classifier.py
tf2pb/tokenization.py
tf2pb/module/__init__.py
tf2pb-0.2.0.dist-info/METADATA
tf2pb-0.2.0.dist-info/WHEEL
tf2pb-0.2.0.dist-info/top_level.txt
tf2pb-0.2.0.dist-info/RECORD
